picture_lake_weibo/ConfigWrapper.py
picture_lake_weibo/MarkdownReplacer.py
picture_lake_weibo/PictureLakeWeibo.py
picture_lake_weibo/Weibo.py
picture_lake_weibo/__init__.py
picture_lake_weibo-0.0.5.dist-info/LICENSE
picture_lake_weibo-0.0.5.dist-info/METADATA
picture_lake_weibo-0.0.5.dist-info/WHEEL
picture_lake_weibo-0.0.5.dist-info/entry_points.txt
picture_lake_weibo-0.0.5.dist-info/top_level.txt
picture_lake_weibo-0.0.5.dist-info/RECORD
