Metadata-Version: 2.1
Name: picture-lake-weibo
Version: 0.0.5
Summary: 把新浪微博作爲圖床
Home-page: https://github.com/wuliang142857/picture-lake-weibo
Author: wuliang142857
Author-email: wuliang142857@gmail.com
License: MIT
Keywords: 圖床
Platform: UNKNOWN
Classifier: Programming Language :: Python :: 3.5
Requires-Dist: rsa (==4.0)
Requires-Dist: requests (==2.22.0)
Requires-Dist: beautifulsoup4 (==4.8.1)
Requires-Dist: Markdown (==3.1.1)
